MANIFEST.in
README.md
setup.py
TradingChartz.egg-info/PKG-INFO
TradingChartz.egg-info/SOURCES.txt
TradingChartz.egg-info/dependency_links.txt
TradingChartz.egg-info/top_level.txt
tradingchartz/__init__.py
tradingchartz/api/__init__.py
tradingchartz/api/data_fetch.py
tradingchartz/apps/__init__.py
tradingchartz/apps/dash/__init__.py
tradingchartz/apps/dash/app.py
tradingchartz/apps/dash/wsgi.py
tradingchartz/apps/dash/dash_components/__init__.py
tradingchartz/apps/dash/dash_components/callbacks.py
tradingchartz/apps/dash/dash_components/charts_and_tables.py
tradingchartz/apps/dash/dash_components/layout.py
tradingchartz/apps/dash/dash_components/store.py
tradingchartz/apps/dash/helpers/__init__.py
tradingchartz/apps/dash/helpers/defaults_and_enums.py
tradingchartz/apps/dash/helpers/helper_functions.py
tradingchartz/apps/python/__init__.py
tradingchartz/apps/python/daily_run.py
tradingchartz/data/NIFTY500_constituents.csv
tradingchartz/data/NIFTY50_constituents.csv
tradingchartz/data/ranking.csv
tradingchartz/src/__init__.py
tradingchartz/src/backtesting/__init__.py
tradingchartz/src/backtesting/data_classes.py
tradingchartz/src/backtesting/default_and_configs.py
tradingchartz/src/backtesting/enums_and_constants.py
tradingchartz/src/backtesting/triple_barrier.py
tradingchartz/src/data_sourcing/__init__.py
tradingchartz/src/data_sourcing/csv_data.py
tradingchartz/src/data_sourcing/data_fetch.py
tradingchartz/src/data_sourcing/nsepy_data.py
tradingchartz/src/data_sourcing/web_paths.py
tradingchartz/src/data_sourcing/yahoo_data.py
tradingchartz/src/helper/__init__.py
tradingchartz/src/helper/web_scrapping.py
tradingchartz/src/signal_and_indicators/__init__.py
tradingchartz/src/signal_and_indicators/signal_generator.py
tradingchartz/unit_tests/__init__.py
tradingchartz/unit_tests/test_nsepydata.py