Metadata-Version: 2.1
Name: TradingChartz
Version: 0.9.8
Summary: Trading back testing and daily signal generation
Home-page: https://github.com/quantsbin/tradingchartz
Author: Quantsbin
Author-email: contactus@quantsbin.com
License: MIT
Platform: UNKNOWN
Classifier: Development Status :: 3 - Alpha
Classifier: Programming Language :: Python :: 3.4
Classifier: Programming Language :: Python :: 3.5
Classifier: Programming Language :: Python :: 3.6
